trunk/Nand_flash_v1/toggle/toggle.v
/**********************************************************

file:  toggle.v

Author:	  albert

date: 2012/05/05

toggle takes 50Mhz clk and passes to PLL module, PLL module will output a 200MHZ once its locked

Static timing analysis @200Mhz verified.

 **********************************************************/
module toggle
(
  input wire clk,reset,enable,
  input wire [11:0]cntUPTO,   
  input wire [4:0] outputVEC1,outputVEC2, //check if we can embedded to a local reg
  output wire done,
  output reg [4:0]outputVEC,
  //output wire pll_locked,   
  output reg dummy_cnt //@@
  
  /*//TestBench signals below
  output wire [1:0]state_tb,
  output wire clk200_tb,
  output wire [3:0]delayCNT_tb,
  output wire [11:0]internalCNT_tb
  //TestBench signals above*/
  );
  
  /*
  //PLL module 
   wire locked;
   wire clk200;
  //PLL instansiate
  pll pll (
   .inclk0(clk),
	.c0(clk200),
	.locked(locked)
	);
	*/
  
  //state declaration
  localparam [1:0]
    toggleWAIT = 2'b00,
	toggle1    = 2'b01,
	toggle2    = 2'b10,
	toggleDONE = 2'b11;
	
	//constant declaration
	localparam TOGGEL_SETUP = 3;  //how many clk cycles needed
	localparam TOGGEL_HOLD  = 2;
	
	
	//signal declaration
	reg [1:0] state_reg, state_next;
	reg [11:0]internalCNT_reg,internalCNT_next;	
	reg [3:0] delayCNT_reg,delayCNT_next; 
	reg toggleDone_reg,toggleDone_next;             //@@
	
	
	//FSM 
	always @ (posedge clk, posedge reset)
	if(reset)
	  begin
	      state_reg <= toggleWAIT;
		  internalCNT_reg <= 0;
		  delayCNT_reg <= 0;
		  toggleDone_reg <=0;
	  end
	 else
	  begin
	      state_reg <=state_next;
		  internalCNT_reg <= internalCNT_next;
		  delayCNT_reg <=delayCNT_next;
		  toggleDone_reg <= toggleDone_next;
	  end
		
	 //FSM next-state logic
	 always @*
	 begin
	   dummy_cnt=0;
	    state_next=state_reg;
		internalCNT_next=internalCNT_reg;
		delayCNT_next=delayCNT_reg;
		toggleDone_next =  toggleDone_reg;
		//outputVEC_enable_next= outputVEC_enable_reg;
		case(state_reg)
		 //
		  toggleWAIT:
		    begin  
			  outputVEC=0;
			  if(enable)
			  //if(enable && locked)
			    begin
			      state_next=toggle1;
				  //outputVEC_enable_next=0;
				  delayCNT_next=0;
				  internalCNT_next=0;
				 end
				else
				 begin
				 //outputVEC_enable_next=0;
			     delayCNT_next=0;
				 internalCNT_next=0;
				 toggleDone_next=0;
				 end
			 end
		//
		  toggle1:
		    begin
			outputVEC=outputVEC1;
			 delayCNT_next=delayCNT_reg+4'd1;
			  if(delayCNT_next==TOGGEL_SETUP)
			    begin
				    state_next=toggle2;
					//outputVEC_enable_next=1;
					internalCNT_next=internalCNT_reg+4'd1;
					dummy_cnt=1;
				end 
			  end
		//
		  toggle2:
		    begin
			 outputVEC=outputVEC2;
			  delayCNT_next=delayCNT_reg+4'd1;
			   if(delayCNT_next== (TOGGEL_SETUP+TOGGEL_HOLD))
				  begin
				   if(internalCNT_reg==cntUPTO)
					 begin
					   state_next=toggleDONE;
						toggleDone_next = 1;
					 end
					else
					  begin
					   state_next=toggle1;
						delayCNT_next=0;
					  end
				  end	  
			 end
		//
		  toggleDONE:
		    begin
			 outputVEC=0;
			  internalCNT_next=0;
		      delayCNT_next=0;
			  if(!enable)
			   begin
			    state_next=toggleWAIT;
				toggleDone_next=0;
			   end
			 end
			default: state_next=toggleWAIT;
		endcase
	end
	
	  
	 assign done=toggleDone_reg;
	 //assign pll_locked=locked;
	 
	 /*//TestBench signals below
	 assign state_tb=state_reg;
	 //assign clk200_tb=clk200;
	 assign delayCNT_tb=delayCNT_reg;
	 assign internalCNT_tb=internalCNT_reg;
	 //TestBench signals above*/

endmodule

Nand_flash_v1/readID/readID.v
/**********************************************************

file:  nand_write.v

Author:	  albert

date: 2012/05/13

Description

 **********************************************************/
module readID
(
  input wire clk,reset,
  output reg IDread_done,
  output reg [7:0] output_data,
  input wire [7:0] input_data,
  
  //testbench signals
  output wire toggleDone_tb,dummy_cnt_tb,
  output wire [1:0] state_reg_tb,IDread_cnt_tb,
  output wire [7:0] DevID_tb,
  output wire [4:0] outputVEC_tb
  //testbench signals
  );
  
  /*
  //PLL module  
   wire locked;
   wire clk150;
  //PLL instansiate
  pll pll (
   .inclk0(clk),
	.c0(clk150),
	.locked(locked)
	);
	*/
	
	//toggle module
	wire [4:0]outputVEC;
	wire toggleDone;
	wire dummy_cnt;
	

  
  //state declaration 
  localparam [1:0]
   readIDwait       = 2'b00,
	readID           = 2'b01,  //latch the cmd
	readIDaddr       = 2'b10, //4 cycle address
	readIDfour       = 2'b11; //wait for 100ns and buffer ready signal

	
	
	//constant declaration
	localparam CMD = 8'h90;
	
	
	//signal declaration
	reg [3:0] state_reg, state_next;
	reg toggle_enable_reg,toggle_enable_next;
	reg [4:0] outputVEC1,outputVEC1_next; // FORMAT: nCE|CLE|ALE|nRE|nWE
   reg [4:0] outputVEC2,outputVEC2_next; // FORMAT: nCE|CLE|ALE|nRE|nWE
   reg [11:0] outputUPTO,outputUPTO_next;
	reg [1:0] IDread_cnt,IDread_cnt_next;
	reg [7:0] DevID;
	
	toggle toggle(
  .clk(clk),
  .reset(reset),
  .enable(toggle_enable_reg),   //input for toggle
  .cntUPTO(outputUPTO),    //input for toggle
  .outputVEC1(outputVEC1), //input for toggle
  .outputVEC2(outputVEC2), //input for toggle
  .done(toggleDone),       
  .outputVEC(outputVEC),
  .dummy_cnt(dummy_cnt)
  ); 
	
	//FSM 
	always @ (posedge clk, posedge reset)
	if(reset)
	  begin
	     state_reg <= readIDwait;
		  toggle_enable_reg <=0;
		  outputVEC1 <= 0;
        outputVEC2 <= 0;
        outputUPTO <= 0; 
		  IDread_cnt <= 0;
	  end
	 else
	  begin
	    state_reg <=state_next;
		 toggle_enable_reg <=toggle_enable_next;
		 outputVEC1 <=outputVEC1_next;
		 outputVEC2 <=outputVEC2_next;
		 outputUPTO <=outputUPTO_next;
       IDread_cnt <=IDread_cnt_next;
		 
	  end
		
	 //FSM next-state logic
	 always @*
	 begin
	    state_next=state_reg;
		 toggle_enable_next=toggle_enable_next;
		 outputVEC1_next=outputVEC1;
		 outputVEC2_next=outputVEC2;
		 outputUPTO_next=outputUPTO;

		case(state_reg)
		 //
		  readIDwait:
		    begin 
			  if( input_data== CMD )
			    begin
			     state_next=readID;
				  outputVEC1_next=5'b10010;
              outputVEC2_next=5'b11010;
              outputUPTO_next=1;
				  output_data=CMD;
				  toggle_enable_next=1;
				 end
				else
				 begin
				 //avoid inferred latch
				 outputVEC1_next=0;
             outputVEC2_next=0;
             outputUPTO_next=0;
				 //reg reset
				 toggle_enable_next=0;
				 IDread_cnt_next=0;
				 IDread_done=0;
				 DevID=0;
				 output_data=0;
				 end
			 end
		//
		  readID:
		    begin
			  if(toggleDone==1) //@@@@@@@@@@@@
			    begin
				  state_next=readIDaddr;
				  outputVEC1_next=5'b10010;
              outputVEC2_next=5'b11100;
              outputUPTO_next=1;
				  output_data=0;
				  toggle_enable_next=1;
				 end
			   else
				 begin
				 outputVEC1_next=5'b10010;
             outputVEC2_next=5'b11010;
             outputUPTO_next=1;
				 output_data=CMD;
				 toggle_enable_next=0;
				 end
			  end
		//
		  readIDaddr:
		    begin
			  if(toggleDone==1) //@@@@@@@@@@@@
			    begin
				   state_next=readIDfour;
					outputVEC1_next=5'b00001;
               outputVEC2_next=5'b00000;
              outputUPTO_next=4;
				  output_data=0;
				  toggle_enable_next=1;
				 end
			   else
				 begin
				 outputVEC1_next=5'b10010;
              outputVEC2_next=5'b11100;
             outputUPTO_next=1;
				 output_data=0;
				 toggle_enable_next=0;
				 end
			 end
		//
		  readIDfour:
		     begin
			  if(toggleDone==1) //@@@@@@@@@@@@
			    begin
				   state_next=readIDwait;
					outputVEC1_next=0;
               outputVEC2_next=0;
               outputUPTO_next=0;
				   IDread_done=1;
				 end
			   else
				 begin
				 if(dummy_cnt==1)
				 begin
				 IDread_cnt_next=IDread_cnt_next+1;
				 DevID=input_data;
				 end
				 outputVEC1_next=5'b00001;
             outputVEC2_next=5'b00000;
             outputUPTO_next=4;
				 output_data=0; //This state is reading the ID, check if need to set to 0
				 toggle_enable_next=0;
				 end
			 end 
			default: state_next=readIDwait;
		endcase
	end
	
	  
	//techbench signals
	  assign toggleDone_tb=toggleDone;
	  assign dummy_cnt_tb=dummy_cnt;
	  assign state_reg_tb=state_reg;
	  assign IDread_cnt_tb=IDread_cnt;
	  assign DevID_tb=DevID;
	  assign outputVEC_tb=outputVEC;
	  
endmodule

trunk/Nand_flash_v1/readID/readID_tb.v
/**********************************************************

file:  my_toggle_tb.v

Author:	  albert

date: 2012/05/05

Purpose: Tested Two operations, 1 singel cycle toggle, 1 four cycles toggle

 **********************************************************/
//Time scale
`timescale 1 ns /  1 ps

module readID_tb ();
  //---------------------------------------------------------
  // inputs to the DUT are reg type
     reg CLOCK_50,reset;
     reg [7:0] input_data;
  
  //--------------------------------------------------------
  // outputs from the DUT are wire type
     wire  [7:0] output_data,DevID_tb;
     wire  IDread_done,toggleDone_tb,dummy_cnt_tb;
	  wire [1:0] state_reg_tb,IDread_cnt_tb;
	  wire [4:0] outputVEC_tb;
	  
	  
  //---------------------------------------------------------
  // instantiate the Device Under Test (DUT)
  // using named instantiation
  readID readID ( 
            .clk(CLOCK_50),  //pll to 200mhz
            .reset(reset),
            .output_data(output_data),
            .input_data(input_data),
            .toggleDone_tb(toggleDone_tb),
            .IDread_done(IDread_done),
				.dummy_cnt_tb(dummy_cnt_tb),
				.state_reg_tb(state_reg_tb),
				.IDread_cnt_tb(IDread_cnt_tb),
				.DevID_tb(DevID_tb),
				.outputVEC_tb(outputVEC_tb)
           );
  //----------------------------------------------------------
  always
    #10 CLOCK_50 = ~CLOCK_50;   
  //-----------------------------------------------------------
  /*****************************************************************************
 	*                  BLOCK 0 -> Reset check                                    *
 	*****************************************************************************/
  // initial blocks are sequential and start at time 0
  initial
  begin                                                  
    // at time 0 reset input value
	 CLOCK_50 = 0; 
	 reset=0;
	 input_data =0;
	 #2000
	 $stop;
  end
  /*****************************************************************************
 	*                  BLOCK 1 -> FSM and Logic test                            *
 	*****************************************************************************/
  //integer i;
  initial 
  begin
	 #200
	 input_data=144;
	 $display("\t\tinput_cmd=%h",input_data); 
	 wait(IDread_done==1)
	 #40
	 $stop;
  end
  
  initial  
  begin
     $dumpfile ("IDread.vcd"); 
     $dumpvars; 
  end 
 
  initial 
  begin
  $monitor("\t\ttime=%d,\tclk=%b,\tstate=%d,\toutput_data=0x%h,\ttoggleDone_tb=%d,\tIDread_done=%b,\tdummy_cnt_tb=%b,\tIDread_cnt_tb=%b,\tDevID_tb=%b,\toutputVEC_tb=%b", $time, CLOCK_50,state_reg_tb,output_data,toggleDone_tb,IDread_done,dummy_cnt_tb,IDread_cnt_tb,DevID_tb,outputVEC_tb);  
  end
  
 
endmodule

trunk/Nand_flash_v1/readID/simulation/modelsim/IDread.vcd
$date
	Sun Jul 29 01:01:25 2012
$end
$version
	ModelSim Version 6.5e
$end
$timescale
	1ps
$end
$scope module readID_tb $end
$var reg 1 ! CLOCK_50 $end
$var reg 1 " reset $end
$var reg 8 # input_data [7:0] $end
$var wire 1 $ output_data [7] $end
$var wire 1 % output_data [6] $end
$var wire 1 & output_data [5] $end
$var wire 1 ' output_data [4] $end
$var wire 1 ( output_data [3] $end
$var wire 1 ) output_data [2] $end
$var wire 1 * output_data [1] $end
$var wire 1 + output_data [0] $end
$var wire 1 , DevID_tb [7] $end
$var wire 1 - DevID_tb [6] $end
$var wire 1 . DevID_tb [5] $end
$var wire 1 / DevID_tb [4] $end
$var wire 1 0 DevID_tb [3] $end
$var wire 1 1 DevID_tb [2] $end
$var wire 1 2 DevID_tb [1] $end
$var wire 1 3 DevID_tb [0] $end
$var wire 1 4 IDread_done $end
$var wire 1 5 toggleDone_tb $end
$var wire 1 6 dummy_cnt_tb $end
$var wire 1 7 state_reg_tb [1] $end
$var wire 1 8 state_reg_tb [0] $end
$var wire 1 9 IDread_cnt_tb [1] $end
$var wire 1 : IDread_cnt_tb [0] $end
$var wire 1 ; outputVEC_tb [4] $end
$var wire 1 < outputVEC_tb [3] $end
$var wire 1 = outputVEC_tb [2] $end
$var wire 1 > outputVEC_tb [1] $end
$var wire 1 ? outputVEC_tb [0] $end
$scope module readID $end
$var parameter 2 @ readIDwait $end
$var parameter 2 A readID $end
$var parameter 2 B readIDaddr $end
$var parameter 2 C readIDfour $end
$var parameter 8 D CMD $end
$var wire 1 E clk $end
$var wire 1 F reset $end
$var reg 1 G IDread_done $end
$var reg 8 H output_data [7:0] $end
$var wire 1 I input_data [7] $end
$var wire 1 J input_data [6] $end
$var wire 1 K input_data [5] $end
$var wire 1 L input_data [4] $end
$var wire 1 M input_data [3] $end
$var wire 1 N input_data [2] $end
$var wire 1 O input_data [1] $end
$var wire 1 P input_data [0] $end
$var wire 1 5 toggleDone_tb $end
$var wire 1 6 dummy_cnt_tb $end
$var wire 1 7 state_reg_tb [1] $end
$var wire 1 8 state_reg_tb [0] $end
$var wire 1 9 IDread_cnt_tb [1] $end
$var wire 1 : IDread_cnt_tb [0] $end
$var wire 1 , DevID_tb [7] $end
$var wire 1 - DevID_tb [6] $end
$var wire 1 . DevID_tb [5] $end
$var wire 1 / DevID_tb [4] $end
$var wire 1 0 DevID_tb [3] $end
$var wire 1 1 DevID_tb [2] $end
$var wire 1 2 DevID_tb [1] $end
$var wire 1 3 DevID_tb [0] $end
$var wire 1 ; outputVEC_tb [4] $end
$var wire 1 < outputVEC_tb [3] $end
$var wire 1 = outputVEC_tb [2] $end
$var wire 1 > outputVEC_tb [1] $end
$var wire 1 ? outputVEC_tb [0] $end
$var wire 1 Q outputVEC [4] $end
$var wire 1 R outputVEC [3] $end
$var wire 1 S outputVEC [2] $end
$var wire 1 T outputVEC [1] $end
$var wire 1 U outputVEC [0] $end
$var wire 1 V toggleDone $end
$var wire 1 W dummy_cnt $end
$var reg 4 X state_reg [3:0] $end
$var reg 4 Y state_next [3:0] $end
$var reg 1 Z toggle_enable_reg $end
$var reg 1 [ toggle_enable_next $end
$var reg 5 \ outputVEC1 [4:0] $end
$var reg 5 ] outputVEC1_next [4:0] $end
$var reg 5 ^ outputVEC2 [4:0] $end
$var reg 5 _ outputVEC2_next [4:0] $end
$var reg 12 ` outputUPTO [11:0] $end
$var reg 12 a outputUPTO_next [11:0] $end
$var reg 2 b IDread_cnt [1:0] $end
$var reg 2 c IDread_cnt_next [1:0] $end
$var reg 8 d DevID [7:0] $end
$scope module toggle $end
$var parameter 2 e toggleWAIT $end
$var parameter 2 f toggle1 $end
$var parameter 2 g toggle2 $end
$var parameter 2 h toggleDONE $end
$var parameter 32 i TOGGEL_SETUP $end
$var parameter 32 j TOGGEL_HOLD $end
$var wire 1 E clk $end
$var wire 1 F reset $end
$var wire 1 k enable $end
$var wire 1 l cntUPTO [11] $end
$var wire 1 m cntUPTO [10] $end
$var wire 1 n cntUPTO [9] $end
$var wire 1 o cntUPTO [8] $end
$var wire 1 p cntUPTO [7] $end
$var wire 1 q cntUPTO [6] $end
$var wire 1 r cntUPTO [5] $end
$var wire 1 s cntUPTO [4] $end
$var wire 1 t cntUPTO [3] $end
$var wire 1 u cntUPTO [2] $end
$var wire 1 v cntUPTO [1] $end
$var wire 1 w cntUPTO [0] $end
$var wire 1 x outputVEC1 [4] $end
$var wire 1 y outputVEC1 [3] $end
$var wire 1 z outputVEC1 [2] $end
$var wire 1 { outputVEC1 [1] $end
$var wire 1 | outputVEC1 [0] $end
$var wire 1 } outputVEC2 [4] $end
$var wire 1 ~ outputVEC2 [3] $end
$var wire 1 !! outputVEC2 [2] $end
$var wire 1 "! outputVEC2 [1] $end
$var wire 1 #! outputVEC2 [0] $end
$var wire 1 V done $end
$var reg 5 $! outputVEC [4:0] $end
$var reg 1 %! dummy_cnt $end
$var reg 2 &! state_reg [1:0] $end
$var reg 2 '! state_next [1:0] $end
$var reg 12 (! internalCNT_reg [11:0] $end
$var reg 12 )! internalCNT_next [11:0] $end
$var reg 4 *! delayCNT_reg [3:0] $end
$var reg 4 +! delayCNT_next [3:0] $end
$var reg 1 ,! toggleDone_reg $end
$var reg 1 -! toggleDone_next $end
$upscope $end
$upscope $end
$upscope $end
$enddefinitions $end
#0
$dumpvars
b0 @
b1 A
b10 B
b11 C
b10010000 D
b0 e
b1 f
b10 g
b11 h
b11 i
b10 j
0!
0"
b0 #
xG
bx H
bx X
b0 Y
xZ
x[
bx \
bx ]
bx ^
bx _
bx `
bx a
bx b
bx c
bx d
bx $!
x%!
bx &!
bx '!
bx (!
bx )!
bx *!
bx +!
x,!
x-!
x+
x*
x)
x(
x'
x&
x%
x$
x3
x2
x1
x0
x/
x.
x-
x,
x4
x5
x6
x8
x7
x:
x9
x?
x>
x=
x<
x;
xU
xT
xS
xR
xQ
xV
xW
0P
0O
0N
0M
0L
0K
0J
0I
0F
0E
x#!
x"!
x!!
x~
x}
x|
x{
xz
xy
xx
xw
xv
xu
xt
xs
xr
xq
xp
xo
xn
xm
xl
xk
$end
#10000
1!
1E
b0 X
08
07
b0 ]
b0 _
b0 a
0[
b0 c
0G
b0 d
b0 H
04
0+
0*
0)
0(
0'
0&
0%
0$
03
02
01
00
0/
0.
0-
0,
#20000
0!
0E
#30000
1!
1E
0Z
b0 \
b0 ^
b0 `
b0 b
0:
09
0k
0w
0v
0u
0t
0s
0r
0q
0p
0o
0n
0m
0l
0#!
0"!
0!!
0~
0}
0|
0{
0z
0y
0x
0%!
b0 '!
0W
06
#40000
0!
0E
#50000
1!
1E
b0 &!
b0 $!
b0 +!
b0 )!
0-!
0U
0T
0S
0R
0Q
0?
0>
0=
0<
0;
#60000
0!
0E
#70000
1!
1E
b0 (!
b0 *!
0,!
0V
05
#80000
0!
0E
#90000
1!
1E
#100000
0!
0E
#110000
1!
1E
#120000
0!
0E
#130000
1!
1E
#140000
0!
0E
#150000
1!
1E
#160000
0!
0E
#170000
1!
1E
#180000
0!
0E
#190000
1!
1E
#200000
b10010000 #
0!
1L
1I
0E
b1 Y
b10010 ]
b11010 _
b1 a
b10010000 H
1[
1'
1$
#210000
1!
1E
b1 X
1Z
b10010 \
b11010 ^
b1 `
18
1k
1w
1"!
1~
1}
1{
1x
b1 '!
0[
#220000
0!
0E
#230000
1!
1E
b1 &!
0Z
0k
b10010 $!
b1 +!
1T
1Q
1>
1;
#240000
0!
0E
#250000
1!
1E
b1 *!
b10 +!
#260000
0!
0E
#270000
1!
1E
b10 *!
b11 +!
b10 '!
b1 )!
1%!
1W
16
#280000
0!
0E
#290000
1!
1E
b10 &!
b1 (!
b11 *!
0%!
b11010 $!
b100 +!
1R
1<
0W
06
#300000
0!
0E
#310000
1!
1E
b100 *!
b101 +!
b11 '!
1-!
#320000
0!
0E
#330000
1!
1E
b11 &!
b101 *!
1,!
1V
15
b10 Y
b11100 _
b0 H
1[
b0 $!
b0 )!
b0 +!
b0 '!
0-!
0T
0R
0Q
0'
0$
0>
0<
0;
#340000
0!
0E
#350000
1!
1E
b0 &!
b0 (!
b0 *!
0,!
b10 X
1Z
b11100 ^
08
17
0V
1k
0"!
1!!
05
0[
b1 '!
#360000
0!
0E
#370000
1!
1E
b1 &!
0Z
0k
b10010 $!
b1 +!
1T
1Q
1>
1;
#380000
0!
0E
#390000
1!
1E
b1 *!
b10 +!
#400000
0!
0E
#410000
1!
1E
b10 *!
b11 +!
b10 '!
b1 )!
1%!
1W
16
#420000
0!
0E
#430000
1!
1E
b10 &!
b1 (!
b11 *!
0%!
b11100 $!
b100 +!
0T
1S
1R
0>
1=
1<
0W
06
#440000
0!
0E
#450000
1!
1E
b100 *!
b101 +!
b11 '!
1-!
#460000
0!
0E
#470000
1!
1E
b11 &!
b101 *!
1,!
1V
15
b11 Y
b1 ]
b0 _
b100 a
1[
b0 $!
b0 )!
b0 +!
b0 '!
0-!
0S
0R
0Q
0=
0<
0;
#480000
0!
0E
#490000
1!
1E
b0 &!
b0 (!
b0 *!
0,!
b11 X
1Z
b1 \
b0 ^
b100 `
18
0V
1k
0w
1u
0!!
0~
0}
1|
0{
0x
05
0[
b1 '!
#500000
0!
0E
#510000
1!
1E
b1 &!
0Z
0k
b1 $!
b1 +!
1U
1?
#520000
0!
0E
#530000
1!
1E
b1 *!
b10 +!
#540000
0!
0E
#550000
1!
1E
b10 *!
b11 +!
b10 '!
b1 )!
1%!
1W
16
b1 c
b10010000 d
1/
1,
#560000
0!
0E
#570000
1!
1E
b10 &!
b1 (!
b11 *!
b1 b
1:
0%!
b0 $!
b100 +!
0U
0?
0W
06
#580000
0!
0E
#590000
1!
1E
b100 *!
b101 +!
b1 '!
b0 +!
#600000
0!
0E
#610000
1!
1E
b1 &!
b0 *!
b1 $!
b1 +!
1U
1?
#620000
0!
0E
#630000
1!
1E
b1 *!
b10 +!
#640000
0!
0E
#650000
1!
1E
b10 *!
b11 +!
b10 '!
b10 )!
1%!
1W
16
b10 c
#660000
0!
0E
#670000
1!
1E
b10 &!
b10 (!
b11 *!
b10 b
0:
19
0%!
b0 $!
b100 +!
0U
0?
0W
06
#680000
0!
0E
#690000
1!
1E
b100 *!
b101 +!
b1 '!
b0 +!
#700000
0!
0E
#710000
1!
1E
b1 &!
b0 *!
b1 $!
b1 +!
1U
1?
#720000
0!
0E
#730000
1!
1E
b1 *!
b10 +!
#740000
0!
0E
#750000
1!
1E
b10 *!
b11 +!
b10 '!
b11 )!
1%!
1W
16
b11 c
#760000
0!
0E
#770000
1!
1E
b10 &!
b11 (!
b11 *!
b11 b
1:
0%!
b0 $!
b100 +!
0U
0?
0W
06
#780000
0!
0E
#790000
1!
1E
b100 *!
b101 +!
b1 '!
b0 +!
#800000
0!
0E
#810000
1!
1E
b1 &!
b0 *!
b1 $!
b1 +!
1U
1?
#820000
0!
0E
#830000
1!
1E
b1 *!
b10 +!
#840000
0!
0E
#850000
1!
1E
b10 *!
b11 +!
b10 '!
b100 )!
1%!
1W
16
b0 c
#860000
0!
0E
#870000
1!
1E
b10 &!
b100 (!
b11 *!
b0 b
0:
09
0%!
b0 $!
b100 +!
0U
0?
0W
06
#880000
0!
0E
#890000
1!
1E
b100 *!
b101 +!
b11 '!
1-!
#900000
0!
0E
#910000
1!
1E
b11 &!
b101 *!
1,!
1V
15
b0 Y
b0 ]
b0 a
1G
b0 )!
b0 +!
b0 '!
0-!
14
#920000
0!
0E
#930000
1!
1E
b0 &!
b0 (!
b0 *!
0,!
b0 X
b0 \
b0 `
08
07
0V
0u
0|
05
b1 Y
b10010 ]
b11010 _
b1 a
b10010000 H
1[
1'
1$
